businessmodels/__init__.py
businessmodels/ai_models.py
businessmodels/customersegmentation.py
businessmodels/get_sla.py
businessmodels/performance_rank.py
businessmodels/price_elasticity.py
businessmodels/recommendation_engine.py
businessmodels/sla_determine.py
businessmodels/sql_server.py
businessmodels-0.3.0.dist-info/licenses/LICENSE
businessmodels-0.3.0.dist-info/METADATA
businessmodels-0.3.0.dist-info/WHEEL
businessmodels-0.3.0.dist-info/top_level.txt
businessmodels-0.3.0.dist-info/RECORD
