Metadata-Version: 2.4
Name: businessmodels
Version: 0.3.0
Summary: It is a Data Science package containing many modules to help in analysis.
Home-page: https://github.com/Business-Brio/businessmodels/tree/main
Author: Business Brio
Author-email: gautam@businessbrio.com
License: MIT
Classifier: Programming Language :: Python :: 3
Classifier: License :: OSI Approved :: MIT License
Classifier: Operating System :: OS Independent
License-File: LICENSE
Requires-Dist: business-models-initial
Dynamic: author
Dynamic: author-email
Dynamic: classifier
Dynamic: description
Dynamic: description-content-type
Dynamic: home-page
Dynamic: license
Dynamic: license-file
Dynamic: requires-dist
Dynamic: summary
